{
  "version": "0.3.14-fixed",
  "steps": [
    {
      "tag": "CreateModel",
      "model": "application"
    },
    {
      "tag": "CreateField",
      "model": "application",
      "field": "accepted",
      "type": "Boolean",
      "arity": "Optional"
    },
    {
      "tag": "CreateDirective",
      "location": {
        "path": {
          "tag": "Field",
          "model": "application",
          "field": "accepted"
        },
        "directive": "default"
      }
    },
    {
      "tag": "CreateArgument",
      "location": {
        "tag": "Directive",
        "path": {
          "tag": "Field",
          "model": "application",
          "field": "accepted"
        },
        "directive": "default"
      },
      "argument": "",
      "value": "false"
    },
    {
      "tag": "CreateField",
      "model": "application",
      "field": "acceptedDate",
      "type": "DateTime",
      "arity": "Optional"
    },
    {
      "tag": "CreateField",
      "model": "application",
      "field": "adminNotes",
      "type": "String",
      "arity": "Optional"
    },
    {
      "tag": "CreateField",
      "model": "application",
      "field": "arrivedDate",
      "type": "DateTime",
      "arity": "Optional"
    },
    {
      "tag": "CreateField",
      "model": "application",
      "field": "canceledDate",
      "type": "DateTime",
      "arity": "Optional"
    },
    {
      "tag": "CreateField",
      "model": "application",
      "field": "created",
      "type": "DateTime",
      "arity": "Optional"
    },
    {
      "tag": "CreateDirective",
      "location": {
        "path": {
          "tag": "Field",
          "model": "application",
          "field": "created"
        },
        "directive": "default"
      }
    },
    {
      "tag": "CreateArgument",
      "location": {
        "tag": "Directive",
        "path": {
          "tag": "Field",
          "model": "application",
          "field": "created"
        },
        "directive": "default"
      },
      "argument": "",
      "value": "now()"
    },
    {
      "tag": "CreateField",
      "model": "application",
      "field": "id",
      "type": "Int",
      "arity": "Required"
    },
    {
      "tag": "CreateDirective",
      "location": {
        "path": {
          "tag": "Field",
          "model": "application",
          "field": "id"
        },
        "directive": "default"
      }
    },
    {
      "tag": "CreateArgument",
      "location": {
        "tag": "Directive",
        "path": {
          "tag": "Field",
          "model": "application",
          "field": "id"
        },
        "directive": "default"
      },
      "argument": "",
      "value": "autoincrement()"
    },
    {
      "tag": "CreateDirective",
      "location": {
        "path": {
          "tag": "Field",
          "model": "application",
          "field": "id"
        },
        "directive": "id"
      }
    },
    {
      "tag": "CreateField",
      "model": "application",
      "field": "inReviewDate",
      "type": "DateTime",
      "arity": "Optional"
    },
    {
      "tag": "CreateField",
      "model": "application",
      "field": "isStaffApplication",
      "type": "Boolean",
      "arity": "Optional"
    },
    {
      "tag": "CreateDirective",
      "location": {
        "path": {
          "tag": "Field",
          "model": "application",
          "field": "isStaffApplication"
        },
        "directive": "default"
      }
    },
    {
      "tag": "CreateArgument",
      "location": {
        "tag": "Directive",
        "path": {
          "tag": "Field",
          "model": "application",
          "field": "isStaffApplication"
        },
        "directive": "default"
      },
      "argument": "",
      "value": "false"
    },
    {
      "tag": "CreateField",
      "model": "application",
      "field": "packetSent",
      "type": "Boolean",
      "arity": "Optional"
    },
    {
      "tag": "CreateDirective",
      "location": {
        "path": {
          "tag": "Field",
          "model": "application",
          "field": "packetSent"
        },
        "directive": "default"
      }
    },
    {
      "tag": "CreateArgument",
      "location": {
        "tag": "Directive",
        "path": {
          "tag": "Field",
          "model": "application",
          "field": "packetSent"
        },
        "directive": "default"
      },
      "argument": "",
      "value": "false"
    },
    {
      "tag": "CreateField",
      "model": "application",
      "field": "postcardSent",
      "type": "Boolean",
      "arity": "Optional"
    },
    {
      "tag": "CreateDirective",
      "location": {
        "path": {
          "tag": "Field",
          "model": "application",
          "field": "postcardSent"
        },
        "directive": "default"
      }
    },
    {
      "tag": "CreateArgument",
      "location": {
        "tag": "Directive",
        "path": {
          "tag": "Field",
          "model": "application",
          "field": "postcardSent"
        },
        "directive": "default"
      },
      "argument": "",
      "value": "false"
    },
    {
      "tag": "CreateField",
      "model": "application",
      "field": "progress",
      "type": "String",
      "arity": "Optional"
    },
    {
      "tag": "CreateField",
      "model": "application",
      "field": "retiredDate",
      "type": "DateTime",
      "arity": "Optional"
    },
    {
      "tag": "CreateField",
      "model": "application",
      "field": "schoolId",
      "type": "Int",
      "arity": "Optional"
    },
    {
      "tag": "CreateField",
      "model": "application",
      "field": "status",
      "type": "String",
      "arity": "Optional"
    },
    {
      "tag": "CreateField",
      "model": "application",
      "field": "submitDate",
      "type": "DateTime",
      "arity": "Optional"
    },
    {
      "tag": "CreateField",
      "model": "application",
      "field": "transferredFromSchool",
      "type": "Int",
      "arity": "Optional"
    },
    {
      "tag": "CreateField",
      "model": "application",
      "field": "userId",
      "type": "Int",
      "arity": "Required"
    },
    {
      "tag": "CreateField",
      "model": "application",
      "field": "school",
      "type": "school",
      "arity": "Optional"
    },
    {
      "tag": "CreateDirective",
      "location": {
        "path": {
          "tag": "Field",
          "model": "application",
          "field": "school"
        },
        "directive": "relation"
      }
    },
    {
      "tag": "CreateArgument",
      "location": {
        "tag": "Directive",
        "path": {
          "tag": "Field",
          "model": "application",
          "field": "school"
        },
        "directive": "relation"
      },
      "argument": "fields",
      "value": "[schoolId]"
    },
    {
      "tag": "CreateArgument",
      "location": {
        "tag": "Directive",
        "path": {
          "tag": "Field",
          "model": "application",
          "field": "school"
        },
        "directive": "relation"
      },
      "argument": "references",
      "value": "[id]"
    },
    {
      "tag": "CreateField",
      "model": "application",
      "field": "user",
      "type": "user",
      "arity": "Required"
    },
    {
      "tag": "CreateDirective",
      "location": {
        "path": {
          "tag": "Field",
          "model": "application",
          "field": "user"
        },
        "directive": "relation"
      }
    },
    {
      "tag": "CreateArgument",
      "location": {
        "tag": "Directive",
        "path": {
          "tag": "Field",
          "model": "application",
          "field": "user"
        },
        "directive": "relation"
      },
      "argument": "fields",
      "value": "[userId]"
    },
    {
      "tag": "CreateArgument",
      "location": {
        "tag": "Directive",
        "path": {
          "tag": "Field",
          "model": "application",
          "field": "user"
        },
        "directive": "relation"
      },
      "argument": "references",
      "value": "[id]"
    },
    {
      "tag": "CreateField",
      "model": "application",
      "field": "applicationadminnote",
      "type": "applicationadminnote",
      "arity": "List"
    },
    {
      "tag": "CreateField",
      "model": "application",
      "field": "applicationanswer",
      "type": "applicationanswer",
      "arity": "List"
    },
    {
      "tag": "CreateField",
      "model": "application",
      "field": "applicationhistory",
      "type": "applicationhistory",
      "arity": "List"
    },
    {
      "tag": "CreateField",
      "model": "application",
      "field": "email",
      "type": "email",
      "arity": "List"
    },
    {
      "tag": "CreateField",
      "model": "application",
      "field": "reference",
      "type": "reference",
      "arity": "List"
    },
    {
      "tag": "CreateDirective",
      "location": {
        "path": {
          "tag": "Model",
          "model": "application",
          "arguments": [
            {
              "name": "",
              "value": "[schoolId]"
            },
            {
              "name": "name",
              "value": "\"schoolId\""
            }
          ]
        },
        "directive": "index"
      }
    },
    {
      "tag": "CreateDirective",
      "location": {
        "path": {
          "tag": "Model",
          "model": "application",
          "arguments": [
            {
              "name": "",
              "value": "[userId]"
            },
            {
              "name": "name",
              "value": "\"userId\""
            }
          ]
        },
        "directive": "index"
      }
    },
    {
      "tag": "CreateModel",
      "model": "applicationadminnote"
    },
    {
      "tag": "CreateField",
      "model": "applicationadminnote",
      "field": "applicationId",
      "type": "Int",
      "arity": "Required"
    },
    {
      "tag": "CreateField",
      "model": "applicationadminnote",
      "field": "author",
      "type": "Int",
      "arity": "Optional"
    },
    {
      "tag": "CreateField",
      "model": "applicationadminnote",
      "field": "created",
      "type": "DateTime",
      "arity": "Optional"
    },
    {
      "tag": "CreateDirective",
      "location": {
        "path": {
          "tag": "Field",
          "model": "applicationadminnote",
          "field": "created"
        },
        "directive": "default"
      }
    },
    {
      "tag": "CreateArgument",
      "location": {
        "tag": "Directive",
        "path": {
          "tag": "Field",
          "model": "applicationadminnote",
          "field": "created"
        },
        "directive": "default"
      },
      "argument": "",
      "value": "now()"
    },
    {
      "tag": "CreateField",
      "model": "applicationadminnote",
      "field": "id",
      "type": "Int",
      "arity": "Required"
    },
    {
      "tag": "CreateDirective",
      "location": {
        "path": {
          "tag": "Field",
          "model": "applicationadminnote",
          "field": "id"
        },
        "directive": "default"
      }
    },
    {
      "tag": "CreateArgument",
      "location": {
        "tag": "Directive",
        "path": {
          "tag": "Field",
          "model": "applicationadminnote",
          "field": "id"
        },
        "directive": "default"
      },
      "argument": "",
      "value": "autoincrement()"
    },
    {
      "tag": "CreateDirective",
      "location": {
        "path": {
          "tag": "Field",
          "model": "applicationadminnote",
          "field": "id"
        },
        "directive": "id"
      }
    },
    {
      "tag": "CreateField",
      "model": "applicationadminnote",
      "field": "modified",
      "type": "DateTime",
      "arity": "Optional"
    },
    {
      "tag": "CreateField",
      "model": "applicationadminnote",
      "field": "note",
      "type": "String",
      "arity": "Optional"
    },
    {
      "tag": "CreateField",
      "model": "applicationadminnote",
      "field": "application",
      "type": "application",
      "arity": "Required"
    },
    {
      "tag": "CreateDirective",
      "location": {
        "path": {
          "tag": "Field",
          "model": "applicationadminnote",
          "field": "application"
        },
        "directive": "relation"
      }
    },
    {
      "tag": "CreateArgument",
      "location": {
        "tag": "Directive",
        "path": {
          "tag": "Field",
          "model": "applicationadminnote",
          "field": "application"
        },
        "directive": "relation"
      },
      "argument": "fields",
      "value": "[applicationId]"
    },
    {
      "tag": "CreateArgument",
      "location": {
        "tag": "Directive",
        "path": {
          "tag": "Field",
          "model": "applicationadminnote",
          "field": "application"
        },
        "directive": "relation"
      },
      "argument": "references",
      "value": "[id]"
    },
    {
      "tag": "CreateField",
      "model": "applicationadminnote",
      "field": "user",
      "type": "user",
      "arity": "Optional"
    },
    {
      "tag": "CreateDirective",
      "location": {
        "path": {
          "tag": "Field",
          "model": "applicationadminnote",
          "field": "user"
        },
        "directive": "relation"
      }
    },
    {
      "tag": "CreateArgument",
      "location": {
        "tag": "Directive",
        "path": {
          "tag": "Field",
          "model": "applicationadminnote",
          "field": "user"
        },
        "directive": "relation"
      },
      "argument": "fields",
      "value": "[author]"
    },
    {
      "tag": "CreateArgument",
      "location": {
        "tag": "Directive",
        "path": {
          "tag": "Field",
          "model": "applicationadminnote",
          "field": "user"
        },
        "directive": "relation"
      },
      "argument": "references",
      "value": "[id]"
    },
    {
      "tag": "CreateDirective",
      "location": {
        "path": {
          "tag": "Model",
          "model": "applicationadminnote",
          "arguments": [
            {
              "name": "",
              "value": "[applicationId]"
            },
            {
              "name": "name",
              "value": "\"applicationId\""
            }
          ]
        },
        "directive": "index"
      }
    },
    {
      "tag": "CreateDirective",
      "location": {
        "path": {
          "tag": "Model",
          "model": "applicationadminnote",
          "arguments": [
            {
              "name": "",
              "value": "[author]"
            },
            {
              "name": "name",
              "value": "\"author\""
            }
          ]
        },
        "directive": "index"
      }
    },
    {
      "tag": "CreateModel",
      "model": "applicationanswer"
    },
    {
      "tag": "CreateField",
      "model": "applicationanswer",
      "field": "answer",
      "type": "String",
      "arity": "Optional"
    },
    {
      "tag": "CreateField",
      "model": "applicationanswer",
      "field": "applicationId",
      "type": "Int",
      "arity": "Optional"
    },
    {
      "tag": "CreateField",
      "model": "applicationanswer",
      "field": "id",
      "type": "Int",
      "arity": "Required"
    },
    {
      "tag": "CreateDirective",
      "location": {
        "path": {
          "tag": "Field",
          "model": "applicationanswer",
          "field": "id"
        },
        "directive": "default"
      }
    },
    {
      "tag": "CreateArgument",
      "location": {
        "tag": "Directive",
        "path": {
          "tag": "Field",
          "model": "applicationanswer",
          "field": "id"
        },
        "directive": "default"
      },
      "argument": "",
      "value": "autoincrement()"
    },
    {
      "tag": "CreateDirective",
      "location": {
        "path": {
          "tag": "Field",
          "model": "applicationanswer",
          "field": "id"
        },
        "directive": "id"
      }
    },
    {
      "tag": "CreateField",
      "model": "applicationanswer",
      "field": "question",
      "type": "String",
      "arity": "Optional"
    },
    {
      "tag": "CreateField",
      "model": "applicationanswer",
      "field": "application",
      "type": "application",
      "arity": "Optional"
    },
    {
      "tag": "CreateDirective",
      "location": {
        "path": {
          "tag": "Field",
          "model": "applicationanswer",
          "field": "application"
        },
        "directive": "relation"
      }
    },
    {
      "tag": "CreateArgument",
      "location": {
        "tag": "Directive",
        "path": {
          "tag": "Field",
          "model": "applicationanswer",
          "field": "application"
        },
        "directive": "relation"
      },
      "argument": "fields",
      "value": "[applicationId]"
    },
    {
      "tag": "CreateArgument",
      "location": {
        "tag": "Directive",
        "path": {
          "tag": "Field",
          "model": "applicationanswer",
          "field": "application"
        },
        "directive": "relation"
      },
      "argument": "references",
      "value": "[id]"
    },
    {
      "tag": "CreateDirective",
      "location": {
        "path": {
          "tag": "Model",
          "model": "applicationanswer",
          "arguments": [
            {
              "name": "",
              "value": "[applicationId]"
            },
            {
              "name": "name",
              "value": "\"applicationId\""
            }
          ]
        },
        "directive": "index"
      }
    },
    {
      "tag": "CreateModel",
      "model": "applicationhistory"
    },
    {
      "tag": "CreateField",
      "model": "applicationhistory",
      "field": "action",
      "type": "String",
      "arity": "Optional"
    },
    {
      "tag": "CreateField",
      "model": "applicationhistory",
      "field": "applicationId",
      "type": "Int",
      "arity": "Required"
    },
    {
      "tag": "CreateField",
      "model": "applicationhistory",
      "field": "created",
      "type": "DateTime",
      "arity": "Optional"
    },
    {
      "tag": "CreateDirective",
      "location": {
        "path": {
          "tag": "Field",
          "model": "applicationhistory",
          "field": "created"
        },
        "directive": "default"
      }
    },
    {
      "tag": "CreateArgument",
      "location": {
        "tag": "Directive",
        "path": {
          "tag": "Field",
          "model": "applicationhistory",
          "field": "created"
        },
        "directive": "default"
      },
      "argument": "",
      "value": "now()"
    },
    {
      "tag": "CreateField",
      "model": "applicationhistory",
      "field": "error",
      "type": "String",
      "arity": "Optional"
    },
    {
      "tag": "CreateField",
      "model": "applicationhistory",
      "field": "field",
      "type": "String",
      "arity": "Optional"
    },
    {
      "tag": "CreateField",
      "model": "applicationhistory",
      "field": "id",
      "type": "Int",
      "arity": "Required"
    },
    {
      "tag": "CreateDirective",
      "location": {
        "path": {
          "tag": "Field",
          "model": "applicationhistory",
          "field": "id"
        },
        "directive": "default"
      }
    },
    {
      "tag": "CreateArgument",
      "location": {
        "tag": "Directive",
        "path": {
          "tag": "Field",
          "model": "applicationhistory",
          "field": "id"
        },
        "directive": "default"
      },
      "argument": "",
      "value": "autoincrement()"
    },
    {
      "tag": "CreateDirective",
      "location": {
        "path": {
          "tag": "Field",
          "model": "applicationhistory",
          "field": "id"
        },
        "directive": "id"
      }
    },
    {
      "tag": "CreateField",
      "model": "applicationhistory",
      "field": "statusNum",
      "type": "String",
      "arity": "Optional"
    },
    {
      "tag": "CreateField",
      "model": "applicationhistory",
      "field": "value",
      "type": "String",
      "arity": "Optional"
    },
    {
      "tag": "CreateField",
      "model": "applicationhistory",
      "field": "application",
      "type": "application",
      "arity": "Required"
    },
    {
      "tag": "CreateDirective",
      "location": {
        "path": {
          "tag": "Field",
          "model": "applicationhistory",
          "field": "application"
        },
        "directive": "relation"
      }
    },
    {
      "tag": "CreateArgument",
      "location": {
        "tag": "Directive",
        "path": {
          "tag": "Field",
          "model": "applicationhistory",
          "field": "application"
        },
        "directive": "relation"
      },
      "argument": "fields",
      "value": "[applicationId]"
    },
    {
      "tag": "CreateArgument",
      "location": {
        "tag": "Directive",
        "path": {
          "tag": "Field",
          "model": "applicationhistory",
          "field": "application"
        },
        "directive": "relation"
      },
      "argument": "references",
      "value": "[id]"
    },
    {
      "tag": "CreateDirective",
      "location": {
        "path": {
          "tag": "Model",
          "model": "applicationhistory",
          "arguments": [
            {
              "name": "",
              "value": "[applicationId]"
            },
            {
              "name": "name",
              "value": "\"applicationId\""
            }
          ]
        },
        "directive": "index"
      }
    },
    {
      "tag": "CreateModel",
      "model": "applicationquestion"
    },
    {
      "tag": "CreateField",
      "model": "applicationquestion",
      "field": "id",
      "type": "Int",
      "arity": "Required"
    },
    {
      "tag": "CreateDirective",
      "location": {
        "path": {
          "tag": "Field",
          "model": "applicationquestion",
          "field": "id"
        },
        "directive": "default"
      }
    },
    {
      "tag": "CreateArgument",
      "location": {
        "tag": "Directive",
        "path": {
          "tag": "Field",
          "model": "applicationquestion",
          "field": "id"
        },
        "directive": "default"
      },
      "argument": "",
      "value": "autoincrement()"
    },
    {
      "tag": "CreateDirective",
      "location": {
        "path": {
          "tag": "Field",
          "model": "applicationquestion",
          "field": "id"
        },
        "directive": "id"
      }
    },
    {
      "tag": "CreateField",
      "model": "applicationquestion",
      "field": "question",
      "type": "String",
      "arity": "Optional"
    },
    {
      "tag": "CreateField",
      "model": "applicationquestion",
      "field": "questionCollectionId",
      "type": "Int",
      "arity": "Required"
    },
    {
      "tag": "CreateField",
      "model": "applicationquestion",
      "field": "applicationQuestionCollection",
      "type": "applicationQuestionCollection",
      "arity": "Required"
    },
    {
      "tag": "CreateDirective",
      "location": {
        "path": {
          "tag": "Field",
          "model": "applicationquestion",
          "field": "applicationQuestionCollection"
        },
        "directive": "relation"
      }
    },
    {
      "tag": "CreateArgument",
      "location": {
        "tag": "Directive",
        "path": {
          "tag": "Field",
          "model": "applicationquestion",
          "field": "applicationQuestionCollection"
        },
        "directive": "relation"
      },
      "argument": "fields",
      "value": "[questionCollectionId]"
    },
    {
      "tag": "CreateArgument",
      "location": {
        "tag": "Directive",
        "path": {
          "tag": "Field",
          "model": "applicationquestion",
          "field": "applicationQuestionCollection"
        },
        "directive": "relation"
      },
      "argument": "references",
      "value": "[id]"
    },
    {
      "tag": "CreateDirective",
      "location": {
        "path": {
          "tag": "Model",
          "model": "applicationquestion",
          "arguments": [
            {
              "name": "",
              "value": "[questionCollectionId]"
            },
            {
              "name": "name",
              "value": "\"questionCollectionId\""
            }
          ]
        },
        "directive": "index"
      }
    },
    {
      "tag": "CreateModel",
      "model": "permission"
    },
    {
      "tag": "CreateField",
      "model": "permission",
      "field": "created",
      "type": "DateTime",
      "arity": "Optional"
    },
    {
      "tag": "CreateDirective",
      "location": {
        "path": {
          "tag": "Field",
          "model": "permission",
          "field": "created"
        },
        "directive": "default"
      }
    },
    {
      "tag": "CreateArgument",
      "location": {
        "tag": "Directive",
        "path": {
          "tag": "Field",
          "model": "permission",
          "field": "created"
        },
        "directive": "default"
      },
      "argument": "",
      "value": "now()"
    },
    {
      "tag": "CreateField",
      "model": "permission",
      "field": "description",
      "type": "String",
      "arity": "Required"
    },
    {
      "tag": "CreateField",
      "model": "permission",
      "field": "id",
      "type": "Int",
      "arity": "Required"
    },
    {
      "tag": "CreateDirective",
      "location": {
        "path": {
          "tag": "Field",
          "model": "permission",
          "field": "id"
        },
        "directive": "default"
      }
    },
    {
      "tag": "CreateArgument",
      "location": {
        "tag": "Directive",
        "path": {
          "tag": "Field",
          "model": "permission",
          "field": "id"
        },
        "directive": "default"
      },
      "argument": "",
      "value": "autoincrement()"
    },
    {
      "tag": "CreateDirective",
      "location": {
        "path": {
          "tag": "Field",
          "model": "permission",
          "field": "id"
        },
        "directive": "id"
      }
    },
    {
      "tag": "CreateField",
      "model": "permission",
      "field": "modified",
      "type": "DateTime",
      "arity": "Optional"
    },
    {
      "tag": "CreateField",
      "model": "permission",
      "field": "name",
      "type": "String",
      "arity": "Optional"
    },
    {
      "tag": "CreateModel",
      "model": "user_information"
    },
    {
      "tag": "CreateField",
      "model": "user_information",
      "field": "children",
      "type": "Int",
      "arity": "Optional"
    },
    {
      "tag": "CreateField",
      "model": "user_information",
      "field": "emRelation",
      "type": "String",
      "arity": "Optional"
    },
    {
      "tag": "CreateField",
      "model": "user_information",
      "field": "eyeColor",
      "type": "String",
      "arity": "Optional"
    },
    {
      "tag": "CreateField",
      "model": "user_information",
      "field": "facebook",
      "type": "String",
      "arity": "Optional"
    },
    {
      "tag": "CreateField",
      "model": "user_information",
      "field": "firstLanguage",
      "type": "String",
      "arity": "Optional"
    },
    {
      "tag": "CreateField",
      "model": "user_information",
      "field": "glutenAllergy",
      "type": "Boolean",
      "arity": "Required"
    },
    {
      "tag": "CreateDirective",
      "location": {
        "path": {
          "tag": "Field",
          "model": "user_information",
          "field": "glutenAllergy"
        },
        "directive": "default"
      }
    },
    {
      "tag": "CreateArgument",
      "location": {
        "tag": "Directive",
        "path": {
          "tag": "Field",
          "model": "user_information",
          "field": "glutenAllergy"
        },
        "directive": "default"
      },
      "argument": "",
      "value": "false"
    },
    {
      "tag": "CreateField",
      "model": "user_information",
      "field": "health",
      "type": "String",
      "arity": "Optional"
    },
    {
      "tag": "CreateField",
      "model": "user_information",
      "field": "height",
      "type": "Int",
      "arity": "Optional"
    },
    {
      "tag": "CreateField",
      "model": "user_information",
      "field": "id",
      "type": "Int",
      "arity": "Required"
    },
    {
      "tag": "CreateDirective",
      "location": {
        "path": {
          "tag": "Field",
          "model": "user_information",
          "field": "id"
        },
        "directive": "default"
      }
    },
    {
      "tag": "CreateArgument",
      "location": {
        "tag": "Directive",
        "path": {
          "tag": "Field",
          "model": "user_information",
          "field": "id"
        },
        "directive": "default"
      },
      "argument": "",
      "value": "autoincrement()"
    },
    {
      "tag": "CreateDirective",
      "location": {
        "path": {
          "tag": "Field",
          "model": "user_information",
          "field": "id"
        },
        "directive": "id"
      }
    },
    {
      "tag": "CreateField",
      "model": "user_information",
      "field": "lactoseAllergy",
      "type": "Boolean",
      "arity": "Required"
    },
    {
      "tag": "CreateDirective",
      "location": {
        "path": {
          "tag": "Field",
          "model": "user_information",
          "field": "lactoseAllergy"
        },
        "directive": "default"
      }
    },
    {
      "tag": "CreateArgument",
      "location": {
        "tag": "Directive",
        "path": {
          "tag": "Field",
          "model": "user_information",
          "field": "lactoseAllergy"
        },
        "directive": "default"
      },
      "argument": "",
      "value": "false"
    },
    {
      "tag": "CreateField",
      "model": "user_information",
      "field": "life",
      "type": "String",
      "arity": "Optional"
    },
    {
      "tag": "CreateField",
      "model": "user_information",
      "field": "maritalStatusDate",
      "type": "DateTime",
      "arity": "Optional"
    },
    {
      "tag": "CreateField",
      "model": "user_information",
      "field": "marriage",
      "type": "String",
      "arity": "Optional"
    },
    {
      "tag": "CreateField",
      "model": "user_information",
      "field": "meds",
      "type": "String",
      "arity": "Optional"
    },
    {
      "tag": "CreateField",
      "model": "user_information",
      "field": "modified",
      "type": "DateTime",
      "arity": "Optional"
    },
    {
      "tag": "CreateField",
      "model": "user_information",
      "field": "moldAllergy",
      "type": "Boolean",
      "arity": "Required"
    },
    {
      "tag": "CreateDirective",
      "location": {
        "path": {
          "tag": "Field",
          "model": "user_information",
          "field": "moldAllergy"
        },
        "directive": "default"
      }
    },
    {
      "tag": "CreateArgument",
      "location": {
        "tag": "Directive",
        "path": {
          "tag": "Field",
          "model": "user_information",
          "field": "moldAllergy"
        },
        "directive": "default"
      },
      "argument": "",
      "value": "false"
    },
    {
      "tag": "CreateField",
      "model": "user_information",
      "field": "nativeLanguage",
      "type": "String",
      "arity": "Optional"
    },
    {
      "tag": "CreateField",
      "model": "user_information",
      "field": "onMedication",
      "type": "Boolean",
      "arity": "Required"
    },
    {
      "tag": "CreateDirective",
      "location": {
        "path": {
          "tag": "Field",
          "model": "user_information",
          "field": "onMedication"
        },
        "directive": "default"
      }
    },
    {
      "tag": "CreateArgument",
      "location": {
        "tag": "Directive",
        "path": {
          "tag": "Field",
          "model": "user_information",
          "field": "onMedication"
        },
        "directive": "default"
      },
      "argument": "",
      "value": "false"
    },
    {
      "tag": "CreateField",
      "model": "user_information",
      "field": "otherFoodAllergy",
      "type": "String",
      "arity": "Optional"
    },
    {
      "tag": "CreateField",
      "model": "user_information",
      "field": "otherLanguage",
      "type": "String",
      "arity": "Optional"
    },
    {
      "tag": "CreateField",
      "model": "user_information",
      "field": "otherLanguagePro",
      "type": "Int",
      "arity": "Optional"
    },
    {
      "tag": "CreateField",
      "model": "user_information",
      "field": "physicalDisability",
      "type": "Boolean",
      "arity": "Required"
    },
    {
      "tag": "CreateDirective",
      "location": {
        "path": {
          "tag": "Field",
          "model": "user_information",
          "field": "physicalDisability"
        },
        "directive": "default"
      }
    },
    {
      "tag": "CreateArgument",
      "location": {
        "tag": "Directive",
        "path": {
          "tag": "Field",
          "model": "user_information",
          "field": "physicalDisability"
        },
        "directive": "default"
      },
      "argument": "",
      "value": "false"
    },
    {
      "tag": "CreateField",
      "model": "user_information",
      "field": "secondLanguage",
      "type": "String",
      "arity": "Optional"
    },
    {
      "tag": "CreateField",
      "model": "user_information",
      "field": "secondLanguagePro",
      "type": "Int",
      "arity": "Optional"
    },
    {
      "tag": "CreateField",
      "model": "user_information",
      "field": "shots",
      "type": "String",
      "arity": "Optional"
    },
    {
      "tag": "CreateField",
      "model": "user_information",
      "field": "spouseName",
      "type": "String",
      "arity": "Optional"
    },
    {
      "tag": "CreateField",
      "model": "user_information",
      "field": "talents",
      "type": "String",
      "arity": "Optional"
    },
    {
      "tag": "CreateField",
      "model": "user_information",
      "field": "thirdLanguage",
      "type": "String",
      "arity": "Optional"
    },
    {
      "tag": "CreateField",
      "model": "user_information",
      "field": "thirdLanguagePro",
      "type": "Int",
      "arity": "Optional"
    },
    {
      "tag": "CreateField",
      "model": "user_information",
      "field": "userId",
      "type": "Int",
      "arity": "Required"
    },
    {
      "tag": "CreateDirective",
      "location": {
        "path": {
          "tag": "Field",
          "model": "user_information",
          "field": "userId"
        },
        "directive": "unique"
      }
    },
    {
      "tag": "CreateField",
      "model": "user_information",
      "field": "website",
      "type": "String",
      "arity": "Optional"
    },
    {
      "tag": "CreateField",
      "model": "user_information",
      "field": "youtube",
      "type": "String",
      "arity": "Optional"
    },
    {
      "tag": "CreateField",
      "model": "user_information",
      "field": "user",
      "type": "user",
      "arity": "Required"
    },
    {
      "tag": "CreateDirective",
      "location": {
        "path": {
          "tag": "Field",
          "model": "user_information",
          "field": "user"
        },
        "directive": "relation"
      }
    },
    {
      "tag": "CreateArgument",
      "location": {
        "tag": "Directive",
        "path": {
          "tag": "Field",
          "model": "user_information",
          "field": "user"
        },
        "directive": "relation"
      },
      "argument": "fields",
      "value": "[userId]"
    },
    {
      "tag": "CreateArgument",
      "location": {
        "tag": "Directive",
        "path": {
          "tag": "Field",
          "model": "user_information",
          "field": "user"
        },
        "directive": "relation"
      },
      "argument": "references",
      "value": "[id]"
    },
    {
      "tag": "DeleteModel",
      "model": "applicationAdminNote"
    },
    {
      "tag": "DeleteModel",
      "model": "applicationAnswer"
    },
    {
      "tag": "DeleteModel",
      "model": "applicationHistory"
    },
    {
      "tag": "DeleteModel",
      "model": "applicationQuestion"
    },
    {
      "tag": "DeleteModel",
      "model": "permissions"
    },
    {
      "tag": "DeleteModel",
      "model": "schoolApplication"
    },
    {
      "tag": "DeleteModel",
      "model": "staffApplication"
    },
    {
      "tag": "DeleteModel",
      "model": "userInformation"
    },
    {
      "tag": "CreateDirective",
      "location": {
        "path": {
          "tag": "Model",
          "model": "address",
          "arguments": [
            {
              "name": "",
              "value": "[nationId]"
            },
            {
              "name": "name",
              "value": "\"nationId\""
            }
          ]
        },
        "directive": "index"
      }
    },
    {
      "tag": "CreateDirective",
      "location": {
        "path": {
          "tag": "Model",
          "model": "address",
          "arguments": [
            {
              "name": "",
              "value": "[userId]"
            },
            {
              "name": "name",
              "value": "\"userId\""
            }
          ]
        },
        "directive": "index"
      }
    },
    {
      "tag": "DeleteDirective",
      "location": {
        "path": {
          "tag": "Model",
          "model": "address",
          "arguments": [
            {
              "name": "",
              "value": "[nationId]"
            },
            {
              "name": "name",
              "value": "\"nation\""
            }
          ]
        },
        "directive": "index"
      }
    },
    {
      "tag": "DeleteDirective",
      "location": {
        "path": {
          "tag": "Model",
          "model": "address",
          "arguments": [
            {
              "name": "",
              "value": "[userId]"
            },
            {
              "name": "name",
              "value": "\"user\""
            }
          ]
        },
        "directive": "index"
      }
    },
    {
      "tag": "CreateField",
      "model": "applicationQuestionCollection",
      "field": "applicationquestion",
      "type": "applicationquestion",
      "arity": "List"
    },
    {
      "tag": "DeleteField",
      "model": "applicationQuestionCollection",
      "field": "applicationQuestion"
    },
    {
      "tag": "CreateDirective",
      "location": {
        "path": {
          "tag": "Model",
          "model": "attachments",
          "arguments": [
            {
              "name": "",
              "value": "[schoolId]"
            },
            {
              "name": "name",
              "value": "\"schoolId\""
            }
          ]
        },
        "directive": "index"
      }
    },
    {
      "tag": "CreateDirective",
      "location": {
        "path": {
          "tag": "Model",
          "model": "attachments",
          "arguments": [
            {
              "name": "",
              "value": "[userId]"
            },
            {
              "name": "name",
              "value": "\"userId\""
            }
          ]
        },
        "directive": "index"
      }
    },
    {
      "tag": "DeleteDirective",
      "location": {
        "path": {
          "tag": "Model",
          "model": "attachments",
          "arguments": [
            {
              "name": "",
              "value": "[schoolId]"
            },
            {
              "name": "name",
              "value": "\"school\""
            }
          ]
        },
        "directive": "index"
      }
    },
    {
      "tag": "DeleteDirective",
      "location": {
        "path": {
          "tag": "Model",
          "model": "attachments",
          "arguments": [
            {
              "name": "",
              "value": "[userId]"
            },
            {
              "name": "name",
              "value": "\"user\""
            }
          ]
        },
        "directive": "index"
      }
    },
    {
      "tag": "UpdateField",
      "model": "child",
      "field": "user",
      "type": "user"
    },
    {
      "tag": "CreateDirective",
      "location": {
        "path": {
          "tag": "Field",
          "model": "child",
          "field": "user"
        },
        "directive": "relation"
      }
    },
    {
      "tag": "CreateArgument",
      "location": {
        "tag": "Directive",
        "path": {
          "tag": "Field",
          "model": "child",
          "field": "user"
        },
        "directive": "relation"
      },
      "argument": "fields",
      "value": "[parent]"
    },
    {
      "tag": "CreateArgument",
      "location": {
        "tag": "Directive",
        "path": {
          "tag": "Field",
          "model": "child",
          "field": "user"
        },
        "directive": "relation"
      },
      "argument": "references",
      "value": "[id]"
    },
    {
      "tag": "UpdateField",
      "model": "child",
      "field": "parent",
      "type": "Int"
    },
    {
      "tag": "DeleteDirective",
      "location": {
        "path": {
          "tag": "Field",
          "model": "child",
          "field": "parent"
        },
        "directive": "relation"
      }
    },
    {
      "tag": "CreateDirective",
      "location": {
        "path": {
          "tag": "Model",
          "model": "child",
          "arguments": [
            {
              "name": "",
              "value": "[parent]"
            },
            {
              "name": "name",
              "value": "\"parent\""
            }
          ]
        },
        "directive": "index"
      }
    },
    {
      "tag": "DeleteDirective",
      "location": {
        "path": {
          "tag": "Model",
          "model": "child",
          "arguments": [
            {
              "name": "",
              "value": "[user]"
            },
            {
              "name": "name",
              "value": "\"user\""
            }
          ]
        },
        "directive": "index"
      }
    },
    {
      "tag": "CreateField",
      "model": "email",
      "field": "applicationId",
      "type": "Int",
      "arity": "Optional"
    },
    {
      "tag": "DeleteField",
      "model": "email",
      "field": "schoolApplication"
    },
    {
      "tag": "UpdateField",
      "model": "email",
      "field": "application",
      "type": "application"
    },
    {
      "tag": "CreateDirective",
      "location": {
        "path": {
          "tag": "Field",
          "model": "email",
          "field": "application"
        },
        "directive": "relation"
      }
    },
    {
      "tag": "CreateArgument",
      "location": {
        "tag": "Directive",
        "path": {
          "tag": "Field",
          "model": "email",
          "field": "application"
        },
        "directive": "relation"
      },
      "argument": "fields",
      "value": "[applicationId]"
    },
    {
      "tag": "CreateArgument",
      "location": {
        "tag": "Directive",
        "path": {
          "tag": "Field",
          "model": "email",
          "field": "application"
        },
        "directive": "relation"
      },
      "argument": "references",
      "value": "[id]"
    },
    {
      "tag": "CreateDirective",
      "location": {
        "path": {
          "tag": "Model",
          "model": "email",
          "arguments": [
            {
              "name": "",
              "value": "[applicationId]"
            },
            {
              "name": "name",
              "value": "\"applicationId\""
            }
          ]
        },
        "directive": "index"
      }
    },
    {
      "tag": "CreateDirective",
      "location": {
        "path": {
          "tag": "Model",
          "model": "email",
          "arguments": [
            {
              "name": "",
              "value": "[schoolId]"
            },
            {
              "name": "name",
              "value": "\"schoolId\""
            }
          ]
        },
        "directive": "index"
      }
    },
    {
      "tag": "DeleteDirective",
      "location": {
        "path": {
          "tag": "Model",
          "model": "email",
          "arguments": [
            {
              "name": "",
              "value": "[application]"
            },
            {
              "name": "name",
              "value": "\"application\""
            }
          ]
        },
        "directive": "index"
      }
    },
    {
      "tag": "DeleteDirective",
      "location": {
        "path": {
          "tag": "Model",
          "model": "email",
          "arguments": [
            {
              "name": "",
              "value": "[schoolId]"
            },
            {
              "name": "name",
              "value": "\"school\""
            }
          ]
        },
        "directive": "index"
      }
    },
    {
      "tag": "CreateField",
      "model": "nation",
      "field": "passport_nationTopassport_birthNationId",
      "type": "passport",
      "arity": "List"
    },
    {
      "tag": "CreateDirective",
      "location": {
        "path": {
          "tag": "Field",
          "model": "nation",
          "field": "passport_nationTopassport_birthNationId"
        },
        "directive": "relation"
      }
    },
    {
      "tag": "CreateArgument",
      "location": {
        "tag": "Directive",
        "path": {
          "tag": "Field",
          "model": "nation",
          "field": "passport_nationTopassport_birthNationId"
        },
        "directive": "relation"
      },
      "argument": "",
      "value": "\"nationTopassport_birthNationId\""
    },
    {
      "tag": "CreateField",
      "model": "nation",
      "field": "passport_nationTopassport_nationId",
      "type": "passport",
      "arity": "List"
    },
    {
      "tag": "CreateDirective",
      "location": {
        "path": {
          "tag": "Field",
          "model": "nation",
          "field": "passport_nationTopassport_nationId"
        },
        "directive": "relation"
      }
    },
    {
      "tag": "CreateArgument",
      "location": {
        "tag": "Directive",
        "path": {
          "tag": "Field",
          "model": "nation",
          "field": "passport_nationTopassport_nationId"
        },
        "directive": "relation"
      },
      "argument": "",
      "value": "\"nationTopassport_nationId\""
    },
    {
      "tag": "DeleteField",
      "model": "nation",
      "field": "passport"
    },
    {
      "tag": "CreateField",
      "model": "passport",
      "field": "birthNationId",
      "type": "Int",
      "arity": "Optional"
    },
    {
      "tag": "CreateField",
      "model": "passport",
      "field": "nation_nationTopassport_birthNationId",
      "type": "nation",
      "arity": "Optional"
    },
    {
      "tag": "CreateDirective",
      "location": {
        "path": {
          "tag": "Field",
          "model": "passport",
          "field": "nation_nationTopassport_birthNationId"
        },
        "directive": "relation"
      }
    },
    {
      "tag": "CreateArgument",
      "location": {
        "tag": "Directive",
        "path": {
          "tag": "Field",
          "model": "passport",
          "field": "nation_nationTopassport_birthNationId"
        },
        "directive": "relation"
      },
      "argument": "",
      "value": "\"nationTopassport_birthNationId\""
    },
    {
      "tag": "CreateArgument",
      "location": {
        "tag": "Directive",
        "path": {
          "tag": "Field",
          "model": "passport",
          "field": "nation_nationTopassport_birthNationId"
        },
        "directive": "relation"
      },
      "argument": "fields",
      "value": "[birthNationId]"
    },
    {
      "tag": "CreateArgument",
      "location": {
        "tag": "Directive",
        "path": {
          "tag": "Field",
          "model": "passport",
          "field": "nation_nationTopassport_birthNationId"
        },
        "directive": "relation"
      },
      "argument": "references",
      "value": "[id]"
    },
    {
      "tag": "CreateField",
      "model": "passport",
      "field": "nation_nationTopassport_nationId",
      "type": "nation",
      "arity": "Optional"
    },
    {
      "tag": "CreateDirective",
      "location": {
        "path": {
          "tag": "Field",
          "model": "passport",
          "field": "nation_nationTopassport_nationId"
        },
        "directive": "relation"
      }
    },
    {
      "tag": "CreateArgument",
      "location": {
        "tag": "Directive",
        "path": {
          "tag": "Field",
          "model": "passport",
          "field": "nation_nationTopassport_nationId"
        },
        "directive": "relation"
      },
      "argument": "",
      "value": "\"nationTopassport_nationId\""
    },
    {
      "tag": "CreateArgument",
      "location": {
        "tag": "Directive",
        "path": {
          "tag": "Field",
          "model": "passport",
          "field": "nation_nationTopassport_nationId"
        },
        "directive": "relation"
      },
      "argument": "fields",
      "value": "[nationId]"
    },
    {
      "tag": "CreateArgument",
      "location": {
        "tag": "Directive",
        "path": {
          "tag": "Field",
          "model": "passport",
          "field": "nation_nationTopassport_nationId"
        },
        "directive": "relation"
      },
      "argument": "references",
      "value": "[id]"
    },
    {
      "tag": "DeleteField",
      "model": "passport",
      "field": "nation"
    },
    {
      "tag": "CreateDirective",
      "location": {
        "path": {
          "tag": "Model",
          "model": "passport",
          "arguments": [
            {
              "name": "",
              "value": "[birthNationId]"
            },
            {
              "name": "name",
              "value": "\"birthNationId\""
            }
          ]
        },
        "directive": "index"
      }
    },
    {
      "tag": "CreateDirective",
      "location": {
        "path": {
          "tag": "Model",
          "model": "passport",
          "arguments": [
            {
              "name": "",
              "value": "[nationId]"
            },
            {
              "name": "name",
              "value": "\"nationId\""
            }
          ]
        },
        "directive": "index"
      }
    },
    {
      "tag": "CreateDirective",
      "location": {
        "path": {
          "tag": "Model",
          "model": "passport",
          "arguments": [
            {
              "name": "",
              "value": "[userId]"
            },
            {
              "name": "name",
              "value": "\"userId\""
            }
          ]
        },
        "directive": "index"
      }
    },
    {
      "tag": "DeleteDirective",
      "location": {
        "path": {
          "tag": "Model",
          "model": "passport",
          "arguments": [
            {
              "name": "",
              "value": "[nationId]"
            },
            {
              "name": "name",
              "value": "\"nation\""
            }
          ]
        },
        "directive": "index"
      }
    },
    {
      "tag": "DeleteDirective",
      "location": {
        "path": {
          "tag": "Model",
          "model": "passport",
          "arguments": [
            {
              "name": "",
              "value": "[userId]"
            },
            {
              "name": "name",
              "value": "\"user\""
            }
          ]
        },
        "directive": "index"
      }
    },
    {
      "tag": "CreateField",
      "model": "reference",
      "field": "applicationId",
      "type": "Int",
      "arity": "Required"
    },
    {
      "tag": "DeleteField",
      "model": "reference",
      "field": "schoolApplication"
    },
    {
      "tag": "UpdateField",
      "model": "reference",
      "field": "application",
      "type": "application"
    },
    {
      "tag": "CreateDirective",
      "location": {
        "path": {
          "tag": "Field",
          "model": "reference",
          "field": "application"
        },
        "directive": "relation"
      }
    },
    {
      "tag": "CreateArgument",
      "location": {
        "tag": "Directive",
        "path": {
          "tag": "Field",
          "model": "reference",
          "field": "application"
        },
        "directive": "relation"
      },
      "argument": "fields",
      "value": "[applicationId]"
    },
    {
      "tag": "CreateArgument",
      "location": {
        "tag": "Directive",
        "path": {
          "tag": "Field",
          "model": "reference",
          "field": "application"
        },
        "directive": "relation"
      },
      "argument": "references",
      "value": "[id]"
    },
    {
      "tag": "CreateDirective",
      "location": {
        "path": {
          "tag": "Model",
          "model": "reference",
          "arguments": [
            {
              "name": "",
              "value": "[applicationId]"
            },
            {
              "name": "name",
              "value": "\"applicationId\""
            }
          ]
        },
        "directive": "index"
      }
    },
    {
      "tag": "DeleteDirective",
      "location": {
        "path": {
          "tag": "Model",
          "model": "reference",
          "arguments": [
            {
              "name": "",
              "value": "[application]"
            },
            {
              "name": "name",
              "value": "\"application\""
            }
          ]
        },
        "directive": "index"
      }
    },
    {
      "tag": "CreateField",
      "model": "school",
      "field": "applicationQuestionCollection",
      "type": "applicationQuestionCollection",
      "arity": "Optional"
    },
    {
      "tag": "CreateDirective",
      "location": {
        "path": {
          "tag": "Field",
          "model": "school",
          "field": "applicationQuestionCollection"
        },
        "directive": "relation"
      }
    },
    {
      "tag": "CreateArgument",
      "location": {
        "tag": "Directive",
        "path": {
          "tag": "Field",
          "model": "school",
          "field": "applicationQuestionCollection"
        },
        "directive": "relation"
      },
      "argument": "fields",
      "value": "[applicationQuestionsId]"
    },
    {
      "tag": "CreateArgument",
      "location": {
        "tag": "Directive",
        "path": {
          "tag": "Field",
          "model": "school",
          "field": "applicationQuestionCollection"
        },
        "directive": "relation"
      },
      "argument": "references",
      "value": "[id]"
    },
    {
      "tag": "CreateField",
      "model": "school",
      "field": "application",
      "type": "application",
      "arity": "List"
    },
    {
      "tag": "DeleteField",
      "model": "school",
      "field": "applicationQuestions"
    },
    {
      "tag": "DeleteField",
      "model": "school",
      "field": "schoolApplication"
    },
    {
      "tag": "CreateDirective",
      "location": {
        "path": {
          "tag": "Model",
          "model": "school",
          "arguments": [
            {
              "name": "",
              "value": "[applicationQuestionsId]"
            },
            {
              "name": "name",
              "value": "\"applicationQuestionsId\""
            }
          ]
        },
        "directive": "index"
      }
    },
    {
      "tag": "DeleteDirective",
      "location": {
        "path": {
          "tag": "Model",
          "model": "school",
          "arguments": [
            {
              "name": "",
              "value": "[applicationQuestionsId]"
            },
            {
              "name": "name",
              "value": "\"applicationQuestions\""
            }
          ]
        },
        "directive": "index"
      }
    },
    {
      "tag": "CreateField",
      "model": "staff",
      "field": "currentSchoolId",
      "type": "Int",
      "arity": "Optional"
    },
    {
      "tag": "DeleteField",
      "model": "staff",
      "field": "schoolId"
    },
    {
      "tag": "UpdateField",
      "model": "staff",
      "field": "school",
      "arity": "Optional"
    },
    {
      "tag": "UpdateArgument",
      "location": {
        "tag": "Directive",
        "path": {
          "tag": "Field",
          "model": "staff",
          "field": "school"
        },
        "directive": "relation"
      },
      "argument": "fields",
      "newValue": "[currentSchoolId]"
    },
    {
      "tag": "CreateDirective",
      "location": {
        "path": {
          "tag": "Model",
          "model": "staff",
          "arguments": [
            {
              "name": "",
              "value": "[currentSchoolId]"
            },
            {
              "name": "name",
              "value": "\"currentSchoolId\""
            }
          ]
        },
        "directive": "index"
      }
    },
    {
      "tag": "CreateDirective",
      "location": {
        "path": {
          "tag": "Model",
          "model": "staff",
          "arguments": [
            {
              "name": "",
              "value": "[userId]"
            },
            {
              "name": "name",
              "value": "\"userId\""
            }
          ]
        },
        "directive": "index"
      }
    },
    {
      "tag": "DeleteDirective",
      "location": {
        "path": {
          "tag": "Model",
          "model": "staff",
          "arguments": [
            {
              "name": "",
              "value": "[schoolId]"
            },
            {
              "name": "name",
              "value": "\"school\""
            }
          ]
        },
        "directive": "index"
      }
    },
    {
      "tag": "DeleteDirective",
      "location": {
        "path": {
          "tag": "Model",
          "model": "staff",
          "arguments": [
            {
              "name": "",
              "value": "[userId]"
            },
            {
              "name": "name",
              "value": "\"user\""
            }
          ]
        },
        "directive": "index"
      }
    },
    {
      "tag": "CreateField",
      "model": "user",
      "field": "application",
      "type": "application",
      "arity": "List"
    },
    {
      "tag": "CreateField",
      "model": "user",
      "field": "applicationadminnote",
      "type": "applicationadminnote",
      "arity": "List"
    },
    {
      "tag": "CreateField",
      "model": "user",
      "field": "user_information",
      "type": "user_information",
      "arity": "Optional"
    },
    {
      "tag": "DeleteField",
      "model": "user",
      "field": "applicationAdminNote"
    },
    {
      "tag": "DeleteField",
      "model": "user",
      "field": "schoolApplication"
    },
    {
      "tag": "DeleteField",
      "model": "user",
      "field": "staffApplication"
    },
    {
      "tag": "DeleteField",
      "model": "user",
      "field": "userInformation"
    }
  ]
}